README.md
setup.py
opencollect/__init__.py
opencollect/main.py
opencollect/reader.py
opencollect/version.py
opencollect/writer.py
opencollect.egg-info/PKG-INFO
opencollect.egg-info/SOURCES.txt
opencollect.egg-info/dependency_links.txt
opencollect.egg-info/requires.txt
opencollect.egg-info/top_level.txt
opencollect/sources/__init__.py
opencollect/sources/client.py