Metadata-Version: 1.1
Name: opencollect
Version: 1.2.1a1
Summary: https://github.com/JamesKBowler/opencollect
Home-page: https://github.com/JamesKBowler/opencollect
Author: James K Bowler
Author-email: james.bowler@datacentauri.com
License: MIT
Project-URL: Source, https://github.com/JamesKBowler/opencollect/
Project-URL: Funding, https://www.cancerresearchuk.org/support-us/donate
Project-URL: Bug Reports, https://github.com/JamesKBowler
Project-URL: Say Thanks!, https://www.linkedin.com/in/jamesbowler/
Keywords: data collection,data mining
Platform: UNKNOWN
Classifier: Development Status :: 3 - Alpha
Classifier: Intended Audience :: Developers
Classifier: Topic :: Software Development :: Build Tools
Classifier: License :: OSI Approved :: MIT License
Classifier: Programming Language :: Python :: 3.5
Classifier: Programming Language :: Python :: 3.6
